VReplacer_Meme_Generator/Generator.py
VReplacer_Meme_Generator/_Helpers.py
VReplacer_Meme_Generator/__init__.py
VReplacer_Meme_Generator-0.2.dist-info/LICENSE.txt
VReplacer_Meme_Generator-0.2.dist-info/METADATA
VReplacer_Meme_Generator-0.2.dist-info/WHEEL
VReplacer_Meme_Generator-0.2.dist-info/top_level.txt
VReplacer_Meme_Generator-0.2.dist-info/RECORD
