Metadata-Version: 2.1
Name: VReplacer-Meme-Generator
Version: 0.2
Summary: Tool for replacing random word in string and generating images
Home-page: https://github.com/DaSzary/vReplacer-meme-generator
License: UNKNOWN
Platform: UNKNOWN
Requires-Python: >=3.9
License-File: LICENSE.txt
